flask_babac/__init__.py
flask_babac/_version.py
flask_babac/flask_babac.py
flask_babac/routes.py
flask_babac/settings.py
Flask_Babac-0.1.0.dist-info/LICENSE.md
Flask_Babac-0.1.0.dist-info/METADATA
Flask_Babac-0.1.0.dist-info/WHEEL
Flask_Babac-0.1.0.dist-info/entry_points.txt
Flask_Babac-0.1.0.dist-info/top_level.txt
Flask_Babac-0.1.0.dist-info/RECORD
