Metadata-Version: 2.1
Name: Flask-Babac
Version: 0.1.0
Summary: A Python3 Flask front-end application to search the Cycle Babac catalogue and return description, price and availability.
Home-page: http://github.com/normcyr/flask_babac
Author: Normand Cyr
Author-email: norm@normandcyr.com
License: GNU GPLv3
Keywords: bicycle babac parts repair diy
Platform: UNKNOWN
Classifier: Development Status :: 3 - Alpha
Classifier: License :: OSI Approved :: GNU General Public License v3 (GPLv3)
Classifier: Programming Language :: Python :: 3
Classifier: Topic :: Office/Business :: Financial
Requires-Python: >=3.5
Requires-Dist: flask
Requires-Dist: recherche-babac2
Requires-Dist: python-dotenv
Requires-Dist: flask-wtf
